{
  "headers": {
    "accept-ranges": "bytes",
    "x-frame-options": "DENY",
    "referrer-policy": "strict-origin-when-cross-origin",
    "age": "23889980",
    "etag": "\"fcedf961bc626fd76a0c85089f1afb10\"",
    "date": "Fri, 29 Dec 2023 23:20:52 GMT",
    "strict-transport-security": "max-age=63072000; includeSubDomains; preload",
    "via": "http/2 edgeproxy-h",
    "content-length": "87",
    "access-control-allow-origin": "*",
    "last-modified": "Fri, 25 Mar 2022 13:32:50 GMT",
    "cross-origin-embedder-policy": "same-origin",
    "x-amz-replication-status": "COMPLETED",
    "content-security-policy": "default-src 'none'; style-src 'unsafe-inline'; sandbox",
    "server": "deno/gcp-europe-west3",
    "vary": "Accept-Encoding, Origin",
    "cache-control": "public, max-age=31536000, immutable",
    "x-amz-cf-pop": "FRA56-P5",
    "cross-origin-opener-policy": "same-origin",
    "server-timing": "fetchSource;dur=30",
    "cross-origin-resource-policy": "same-origin",
    "content-type": "application/typescript; charset=utf-8",
    "x-cache": "Hit from cloudfront",
    "x-content-type-options": "nosniff",
    "x-amz-cf-id": "7vlxOAHdJ6Dc9sipb2DWEfKEKmMkNTaKXB4wZWLnWYruLACfVF7nzQ==",
    "x-amz-version-id": "RjXukEQkaFJEOMf9fny0Z_wcu7qNC.Vq"
  },
  "url": "https://deno.land/std@0.132.0/node/internal_binding/timers.ts",
  "now": {
    "secs_since_epoch": 1727782031,
    "nanos_since_epoch": 388746827
  }
}