{
  "headers": {
    "last-modified": "Fri, 25 Mar 2022 13:32:48 GMT",
    "date": "Tue, 16 Jan 2024 06:30:38 GMT",
    "server": "deno/gcp-europe-west3",
    "content-length": "1483",
    "strict-transport-security": "max-age=63072000; includeSubDomains; preload",
    "cross-origin-embedder-policy": "same-origin",
    "accept-ranges": "bytes",
    "age": "22395394",
    "referrer-policy": "strict-origin-when-cross-origin",
    "vary": "Accept-Encoding, Origin",
    "via": "http/2 edgeproxy-h",
    "x-frame-options": "DENY",
    "access-control-allow-origin": "*",
    "content-security-policy": "default-src 'none'; style-src 'unsafe-inline'; sandbox",
    "etag": "\"d07874cf507fc1f6ee5fe1d6992d797d\"",
    "server-timing": "fetchSource;dur=8",
    "x-cache": "Hit from cloudfront",
    "cross-origin-opener-policy": "same-origin",
    "cross-origin-resource-policy": "same-origin",
    "x-amz-cf-id": "MHFIduphbLxX3uJ07Thfq2r6SSmsQaFkZIMX4Y_kVwfIZZW__SyKBw==",
    "cache-control": "public, max-age=31536000, immutable",
    "content-type": "application/typescript; charset=utf-8",
    "x-amz-cf-pop": "FRA56-P5",
    "x-amz-replication-status": "COMPLETED",
    "x-amz-version-id": "EiYfF7o0tDDjdDbNAr0FkHt25ydqo4KG",
    "x-content-type-options": "nosniff"
  },
  "url": "https://deno.land/std@0.132.0/node/_crypto/randomInt.ts",
  "now": {
    "secs_since_epoch": 1727782031,
    "nanos_since_epoch": 257139322
  }
}